birdie/__init__.py
birdie/__version__.py
birdie/input.py
birdie/server.py
birdie/chat/__init__.py
birdie/chat/input.py
birdie/chat/output.py
birdie_python_sdk-0.1.0.dist-info/licenses/LICENSE
birdie_python_sdk-0.1.0.dist-info/METADATA
birdie_python_sdk-0.1.0.dist-info/WHEEL
birdie_python_sdk-0.1.0.dist-info/top_level.txt
birdie_python_sdk-0.1.0.dist-info/RECORD
