Metadata-Version: 2.4
Name: birdie-python-sdk
Version: 0.1.0
Summary: Add your description here
Requires-Python: >=3.13
License-File: LICENSE
Requires-Dist: fastapi>=0.119.0
Dynamic: license-file
